[{
		"categoryId" : "1000",
		"categoryName" : "1000",
		"categoryLevel" : "1",
		"categoryIconUrl" : "resources/icons/defaultIcon.png",
		"categoryStyle" : "parentCategory",
		"arg_1" : "1001",
		"arg_2" : "1002",
		"arg_3" : "1003",
	}, {
		"categoryId" : "1001",
		"categoryName" : "1001",
		"categoryLevel" : "2",
		"categoryIconUrl" : "resources/icons/defaultIcon.png",
		"categoryStyle" : "childCategory",
	}, {
		"categoryId" : "1002",
		"categoryName" : "1002",
		"categoryLevel" : "2",
		"categoryIconUrl" : "resources/icons/defaultIcon.png",
		"categoryStyle" : "childCategory",
	}, {
		"categoryId" : "1003",
		"categoryName" : "1003",
		"categoryLevel" : "2",
		"categoryIconUrl" : "resources/icons/defaultIcon.png",
		"categoryStyle" : "childCategory",
	}, {
		"categoryId" : "1004",
		"categoryName" : "1004",
		"categoryLevel" : "1",
		"categoryIconUrl" : "resources/icons/defaultIcon.png",
		"categoryStyle" : "childCategory",
	}, {
		"categoryId" : "1005",
		"categoryName" : "1005",
		"categoryLevel" : "1",
		"categoryIconUrl" : "resources/icons/defaultIcon.png",
		"categoryStyle" : "childCategory",
	}, {
		"categoryId" : "1006",
		"categoryName" : "1006",
		"categoryLevel" : "1",
		"categoryIconUrl" : "resources/icons/defaultIcon.png",
		"categoryStyle" : "childCategory",
	}, {
		"categoryId" : "1007",
		"categoryName" : "1007",
		"categoryLevel" : "1",
		"categoryIconUrl" : "resources/icons/defaultIcon.png",
		"categoryStyle" : "childCategory",
	}, {
		"categoryId" : "1008",
		"categoryName" : "1008",
		"categoryLevel" : "1",
		"categoryIconUrl" : "resources/icons/defaultIcon.png",
		"categoryStyle" : "childCategory",
	}, {
		"categoryId" : "1009",
		"categoryName" : "1009",
		"categoryLevel" : "1",
		"categoryIconUrl" : "resources/icons/defaultIcon.png",
		"categoryStyle" : "childCategory",
	}, {
		"categoryId" : "1010",
		"categoryName" : "1010",
		"categoryLevel" : "1",
		"categoryIconUrl" : "resources/icons/defaultIcon.png",
		"categoryStyle" : "childCategory",
	}, {
		"categoryId" : "1011",
		"categoryName" : "1011",
		"categoryLevel" : "1",
		"categoryIconUrl" : "resources/icons/defaultIcon.png",
		"categoryStyle" : "childCategory",
	},
]
